OpenNTFY/OpenNTFY.py
OpenNTFY/__init__.py
OpenNTFY/_telegram_config.py
OpenNTFY-0.1.2.dist-info/LICENSE
OpenNTFY-0.1.2.dist-info/METADATA
OpenNTFY-0.1.2.dist-info/WHEEL
OpenNTFY-0.1.2.dist-info/entry_points.txt
OpenNTFY-0.1.2.dist-info/top_level.txt
OpenNTFY-0.1.2.dist-info/RECORD
